paddleseg/__init__.py
paddleseg/core/__init__.py
paddleseg/core/infer.py
paddleseg/core/predict.py
paddleseg/core/train.py
paddleseg/core/val.py
paddleseg/cvlibs/__init__.py
paddleseg/cvlibs/builder.py
paddleseg/cvlibs/callbacks.py
paddleseg/cvlibs/config.py
paddleseg/cvlibs/config_checker.py
paddleseg/cvlibs/manager.py
paddleseg/cvlibs/param_init.py
paddleseg/datasets/__init__.py
paddleseg/datasets/ade.py
paddleseg/datasets/chase_db1.py
paddleseg/datasets/cityscapes.py
paddleseg/datasets/cocostuff.py
paddleseg/datasets/dataset.py
paddleseg/datasets/drive.py
paddleseg/datasets/eg1800.py
paddleseg/datasets/hrf.py
paddleseg/datasets/mini_deep_globe_road_extraction.py
paddleseg/datasets/optic_disc_seg.py
paddleseg/datasets/pascal_context.py
paddleseg/datasets/pp_humanseg14k.py
paddleseg/datasets/pssl.py
paddleseg/datasets/stare.py
paddleseg/datasets/supervisely.py
paddleseg/datasets/voc.py
paddleseg/deploy/__init__.py
paddleseg/deploy/export.py
paddleseg/deploy/infer.py
paddleseg/models/__init__.py
paddleseg/models/ann.py
paddleseg/models/attention_unet.py
paddleseg/models/bisenet.py
paddleseg/models/bisenetv1.py
paddleseg/models/ccnet.py
paddleseg/models/danet.py
paddleseg/models/ddrnet.py
paddleseg/models/decoupled_segnet.py
paddleseg/models/deeplab.py
paddleseg/models/dmnet.py
paddleseg/models/dnlnet.py
paddleseg/models/emanet.py
paddleseg/models/encnet.py
paddleseg/models/enet.py
paddleseg/models/espnet.py
paddleseg/models/espnetv1.py
paddleseg/models/fast_scnn.py
paddleseg/models/fastfcn.py
paddleseg/models/fcn.py
paddleseg/models/gcnet.py
paddleseg/models/ginet.py
paddleseg/models/glore.py
paddleseg/models/gscnn.py
paddleseg/models/hardnet.py
paddleseg/models/hrnet_contrast.py
paddleseg/models/isanet.py
paddleseg/models/knet.py
paddleseg/models/lpsnet.py
paddleseg/models/lraspp.py
paddleseg/models/maskformer.py
paddleseg/models/mla_transformer.py
paddleseg/models/mobileseg.py
paddleseg/models/mscale_ocrnet.py
paddleseg/models/ocrnet.py
paddleseg-2.8.0.dist-info/LICENSE
paddleseg-2.8.0.dist-info/METADATA
paddleseg-2.8.0.dist-info/WHEEL
paddleseg-2.8.0.dist-info/top_level.txt
paddleseg-2.8.0.dist-info/RECORD
