Metadata-Version: 2.1
Name: paddleseg
Version: 2.8.0
Summary: End-to-end image segmentation kit based on PaddlePaddle.
Home-page: https://github.com/PaddlePaddle/PaddleSeg
Author: PaddlePaddle Author
Author-email: 
License: Apache 2.0
Keywords: paddleseg paddlepaddle semantic-segmentation instance-segmentation
Platform: UNKNOWN
Classifier: Development Status :: 4 - Beta
Classifier: Intended Audience :: Developers
Classifier: Intended Audience :: Education
Classifier: Intended Audience :: Science/Research
Classifier: License :: OSI Approved :: Apache Software License
Classifier: Programming Language :: Python :: 3.6
Classifier: Programming Language :: Python :: 3.7
Classifier: Topic :: Scientific/Engineering
Classifier: Topic :: Scientific/Engineering :: Mathematics
Classifier: Topic :: Scientific/Engineering :: Artificial Intelligence
Classifier: Topic :: Software Development
Classifier: Topic :: Software Development :: Libraries
Classifier: Topic :: Software Development :: Libraries :: Python Modules
License-File: LICENSE
Requires-Dist: pyyaml (>=5.1)
Requires-Dist: visualdl (>=2.2.0)
Requires-Dist: opencv-python (<=4.6.0)
Requires-Dist: tqdm
Requires-Dist: filelock
Requires-Dist: scipy
Requires-Dist: prettytable
Requires-Dist: scikit-learn
